pyf.api-1.0.0.dev0-py3.7-nspkg.pth
pyf/api/__init__.py
pyf/api/search.py
pyf/api/utils.py
pyf/api/tests/__init__.py
pyf/api/tests/test_view_base.py
pyf/api/views/__init__.py
pyf/api/views/base.py
pyf/api/views/search.py
pyf.api-1.0.0.dev0.dist-info/AUTHORS.rst
pyf.api-1.0.0.dev0.dist-info/LICENSE
pyf.api-1.0.0.dev0.dist-info/METADATA
pyf.api-1.0.0.dev0.dist-info/WHEEL
pyf.api-1.0.0.dev0.dist-info/entry_points.txt
pyf.api-1.0.0.dev0.dist-info/namespace_packages.txt
pyf.api-1.0.0.dev0.dist-info/top_level.txt
pyf.api-1.0.0.dev0.dist-info/RECORD
