Metadata-Version: 2.1
Name: pyf.api
Version: 1.0.0.dev0
Summary: Python Package Filter API
Home-page: https://pypi.python.org/pypi/pyf.api
Author: 
Author-email: 
License: GNU General Public License v2 (GPLv2)
Keywords: Python Buildout Extension
Platform: UNKNOWN
Classifier: Framework :: Pyramid
Classifier: Intended Audience :: Developers
Classifier: License :: OSI Approved :: Apache Software License
Classifier: Operating System :: OS Independent
Classifier: Programming Language :: Python
Classifier: Programming Language :: Python :: 3.6
Classifier: Programming Language :: Python :: 3.7
Classifier: Topic :: Internet :: WWW/HTTP :: Dynamic Content
Requires-Dist: cornice
Requires-Dist: elasticsearch-dsl
Requires-Dist: pyramid
Requires-Dist: setuptools
Provides-Extra: dev
Requires-Dist: pyramid-debugtoolbar ; extra == 'dev'
Requires-Dist: pdbpp ; extra == 'dev'
Provides-Extra: testing
Requires-Dist: responses ; extra == 'testing'
Requires-Dist: webtest ; extra == 'testing'
Requires-Dist: pytest ; extra == 'testing'
Requires-Dist: pytest-cov ; extra == 'testing'
